<?xml version="1.0" encoding="utf-8"?>
<items termsofuse="https://boardgamegeek.com/xmlapi/termsofuse">
  <item type="boardgameexpansion" id="10991">
    <thumbnail>https://cf.geekdo-images.com/thumb/img/drQpWA0W5qohZON82vit3AWx26Y=/fit-in/200x150/pic1140882.jpg</thumbnail>
    <image>https://cf.geekdo-images.com/original/img/f6m0Xy-RqCTz2QfyspM2IygGOsk=/0x0/pic1140882.jpg</image>
    <name type="primary" sortindex="1" value="WarCraft: The Board Game Expansion Set"/>
    <name type="alternate" sortindex="1" value="WarCraft: The Board Game Boîte D'Extension"/>
    <name type="alternate" sortindex="1" value="WarCraft: The Board Game Erweiterung"/>
    <name type="alternate" sortindex="1" value="WarCraft: The Boardgame Uitbreiding"/>
    <description>Only the Ruthless Survive!&amp;#10;&amp;#10;Warcraft: The Board Game receives its highly-anticipated expansion! The Warcraft Expansion Set includes a multitude of exciting and flavorful new options for your Warcraft board game experience.&amp;#10;&amp;#10;* New rules and components for the sixteen Warcraft heroes&amp;#10;    * Random &amp;ldquo;creep&amp;rdquo; encounters&amp;#10;    * New special race decks&amp;#10;    * New specialized board tiles&amp;#10;    * New scenarios&amp;#10;    * New resource system&amp;#10;&amp;#10;For countless hours of brutal fantasy fun!&amp;#10;&amp;#10;The Warcraft Expansion Set requires WarCraft: The Board Game to play.&amp;#10;&amp;#10;Expands:&amp;#10;&amp;#10;    WarCraft: The Board Game&amp;#10;&amp;#10;&amp;#10;&amp;#10;&amp;#10;</description>
    <yearpublished value="2004"/>
    <minplayers value="2"/>
    <maxplayers value="4"/>
    <poll name="suggested_numplayers" title="User Suggested Number of Players" totalvotes="8">
      <results numplayers="1">
        <result value="Best" numvotes="0"/>
        <result value="Recommended" numvotes="0"/>
        <result value="Not Recommended" numvotes="5"/>
      </results>
      <results numplayers="2">
        <result value="Best" numvotes="4"/>
        <result value="Recommended" numvotes="3"/>
        <result value="Not Recommended" numvotes="0"/>
      </results>
      <results numplayers="3">
        <result value="Best" numvotes="0"/>
        <result value="Recommended" numvotes="4"/>
        <result value="Not Recommended" numvotes="4"/>
      </results>
      <results numplayers="4">
        <result value="Best" numvotes="5"/>
        <result value="Recommended" numvotes="2"/>
        <result value="Not Recommended" numvotes="0"/>
      </results>
      <results numplayers="4+">
        <result value="Best" numvotes="0"/>
        <result value="Recommended" numvotes="0"/>
        <result value="Not Recommended" numvotes="4"/>
      </results>
    </poll>
    <playingtime value="90"/>
    <minplaytime value="90"/>
    <maxplaytime value="90"/>
    <minage value="10"/>
    <poll name="suggested_playerage" title="User Suggested Player Age" totalvotes="4">
      <results>
        <result value="2" numvotes="0"/>
        <result value="3" numvotes="0"/>
        <result value="4" numvotes="0"/>
        <result value="5" numvotes="0"/>
        <result value="6" numvotes="0"/>
        <result value="8" numvotes="0"/>
        <result value="10" numvotes="1"/>
        <result value="12" numvotes="2"/>
        <result value="14" numvotes="1"/>
        <result value="16" numvotes="0"/>
        <result value="18" numvotes="0"/>
        <result value="21 and up" numvotes="0"/>
      </results>
    </poll>
    <poll name="language_dependence" title="Language Dependence" totalvotes="4">
      <results>
        <result level="1" value="No necessary in-game text" numvotes="0"/>
        <result level="2" value="Some necessary text - easily memorized or small crib sheet" numvotes="0"/>
        <result level="3" value="Moderate in-game text - needs crib sheet or paste ups" numvotes="4"/>
        <result level="4" value="Extensive use of text - massive conversion needed to be playable" numvotes="0"/>
        <result level="5" value="Unplayable in another language" numvotes="0"/>
      </results>
    </poll>
    <link type="boardgamecategory" id="1042" value="Expansion for Base-game"/>
    <link type="boardgamecategory" id="1010" value="Fantasy"/>
    <link type="boardgamecategory" id="1046" value="Fighting"/>
    <link type="boardgamecategory" id="1101" value="Video Game Theme"/>
    <link type="boardgamecategory" id="1019" value="Wargame"/>
    <link type="boardgamemechanic" id="2072" value="Dice Rolling"/>
    <link type="boardgamemechanic" id="2011" value="Modular Board"/>
    <link type="boardgamemechanic" id="2015" value="Variable Player Powers"/>
    <link type="boardgamefamily" id="5013" value="Warcraft"/>
    <link type="boardgameexpansion" id="7479" value="WarCraft: The Board Game" inbound="true"/>
    <link type="boardgamedesigner" id="2336" value="Kevin Wilson"/>
    <link type="boardgameartist" id="7483" value="John Goodenough"/>
    <link type="boardgameartist" id="12017" value="Scott Nicely"/>
    <link type="boardgameartist" id="11989" value="Brian Schomburg"/>
    <link type="boardgamepublisher" id="17" value="Fantasy Flight Games"/>
    <link type="boardgamepublisher" id="264" value="Heidelberger Spieleverlag"/>
    <link type="boardgamepublisher" id="3446" value="Ubik"/>
    <statistics page="1">
      <ratings>
        <usersrated value="695"/>
        <average value="6.87058"/>
        <bayesaverage value="5.93866"/>
        <ranks>
          <rank type="subtype" id="1" name="boardgame" friendlyname="Board Game Rank" value="Not Ranked" bayesaverage="5.93866"/>
          <rank type="family" id="4664" name="wargames" friendlyname="War Game Rank" value="Not Ranked" bayesaverage="6.32975"/>
          <rank type="family" id="5496" name="thematic" friendlyname="Thematic Rank" value="Not Ranked" bayesaverage="6.14272"/>
        </ranks>
        <stddev value="1.43075"/>
        <median value="0"/>
        <owned value="1770"/>
        <trading value="95"/>
        <wanting value="45"/>
        <wishing value="102"/>
        <numcomments value="242"/>
        <numweights value="80"/>
        <averageweight value="2.875"/>
      </ratings>
    </statistics>
  </item>
</items>
