<?xml version="1.0" encoding="utf-8"?>
<items termsofuse="https://boardgamegeek.com/xmlapi/termsofuse">
  <item type="boardgameexpansion" id="40675">
    <thumbnail>https://cf.geekdo-images.com/thumb/img/f2hVwE4Yv49YVLw6TCcdKGRD_KA=/fit-in/200x150/pic588608.jpg</thumbnail>
    <image>https://cf.geekdo-images.com/original/img/XWH77hp7RnHPsl95_4YbcnQAiIY=/0x0/pic588608.jpg</image>
    <name type="primary" sortindex="1" value="Your Own Private Idaho"/>
    <description>Your Own Private Idaho is an expansion module for the game Price of Freedom from West End Games which can be played either as a role-playing game or as a hex and counter wargame.&amp;#10;&amp;#10;Your Own Private Idaho includes rules for helicopters and anti-aircraft weapons, new maps, and a detailed scenario.&amp;#10;&amp;#10;</description>
    <yearpublished value="1987"/>
    <minplayers value="1"/>
    <maxplayers value="15"/>
    <poll name="suggested_numplayers" title="User Suggested Number of Players" totalvotes="0">
      <results numplayers="1">
        <result value="Best" numvotes="0"/>
        <result value="Recommended" numvotes="0"/>
        <result value="Not Recommended" numvotes="0"/>
      </results>
      <results numplayers="2">
        <result value="Best" numvotes="0"/>
        <result value="Recommended" numvotes="0"/>
        <result value="Not Recommended" numvotes="0"/>
      </results>
      <results numplayers="3">
        <result value="Best" numvotes="0"/>
        <result value="Recommended" numvotes="0"/>
        <result value="Not Recommended" numvotes="0"/>
      </results>
      <results numplayers="4">
        <result value="Best" numvotes="0"/>
        <result value="Recommended" numvotes="0"/>
        <result value="Not Recommended" numvotes="0"/>
      </results>
      <results numplayers="5">
        <result value="Best" numvotes="0"/>
        <result value="Recommended" numvotes="0"/>
        <result value="Not Recommended" numvotes="0"/>
      </results>
      <results numplayers="6">
        <result value="Best" numvotes="0"/>
        <result value="Recommended" numvotes="0"/>
        <result value="Not Recommended" numvotes="0"/>
      </results>
      <results numplayers="7">
        <result value="Best" numvotes="0"/>
        <result value="Recommended" numvotes="0"/>
        <result value="Not Recommended" numvotes="0"/>
      </results>
      <results numplayers="8">
        <result value="Best" numvotes="0"/>
        <result value="Recommended" numvotes="0"/>
        <result value="Not Recommended" numvotes="0"/>
      </results>
      <results numplayers="9">
        <result value="Best" numvotes="0"/>
        <result value="Recommended" numvotes="0"/>
        <result value="Not Recommended" numvotes="0"/>
      </results>
      <results numplayers="10">
        <result value="Best" numvotes="0"/>
        <result value="Recommended" numvotes="0"/>
        <result value="Not Recommended" numvotes="0"/>
      </results>
      <results numplayers="11">
        <result value="Best" numvotes="0"/>
        <result value="Recommended" numvotes="0"/>
        <result value="Not Recommended" numvotes="0"/>
      </results>
      <results numplayers="12">
        <result value="Best" numvotes="0"/>
        <result value="Recommended" numvotes="0"/>
        <result value="Not Recommended" numvotes="0"/>
      </results>
      <results numplayers="13">
        <result value="Best" numvotes="0"/>
        <result value="Recommended" numvotes="0"/>
        <result value="Not Recommended" numvotes="0"/>
      </results>
      <results numplayers="14">
        <result value="Best" numvotes="0"/>
        <result value="Recommended" numvotes="0"/>
        <result value="Not Recommended" numvotes="0"/>
      </results>
      <results numplayers="15">
        <result value="Best" numvotes="0"/>
        <result value="Recommended" numvotes="0"/>
        <result value="Not Recommended" numvotes="0"/>
      </results>
      <results numplayers="15+">
        <result value="Best" numvotes="0"/>
        <result value="Recommended" numvotes="0"/>
        <result value="Not Recommended" numvotes="0"/>
      </results>
    </poll>
    <playingtime value="0"/>
    <minplaytime value="0"/>
    <maxplaytime value="0"/>
    <minage value="0"/>
    <poll name="suggested_playerage" title="User Suggested Player Age" totalvotes="0">
	</poll>
    <poll name="language_dependence" title="Language Dependence" totalvotes="0">
	</poll>
    <link type="boardgamecategory" id="1022" value="Adventure"/>
    <link type="boardgamecategory" id="1042" value="Expansion for Base-game"/>
    <link type="boardgamecategory" id="1047" value="Miniatures"/>
    <link type="boardgamecategory" id="1069" value="Modern Warfare"/>
    <link type="boardgamecategory" id="1019" value="Wargame"/>
    <link type="boardgamemechanic" id="2001" value="Action Point Allowance System"/>
    <link type="boardgamemechanic" id="2023" value="Cooperative Play"/>
    <link type="boardgamemechanic" id="2026" value="Hex-and-Counter"/>
    <link type="boardgamemechanic" id="2055" value="Paper-and-Pencil"/>
    <link type="boardgamemechanic" id="2028" value="Role Playing"/>
    <link type="boardgamemechanic" id="2016" value="Secret Unit Deployment"/>
    <link type="boardgamemechanic" id="2020" value="Simultaneous Action Selection"/>
    <link type="boardgameexpansion" id="40634" value="Price of Freedom" inbound="true"/>
    <link type="boardgamedesigner" id="498" value="Greg Costikyan"/>
    <link type="boardgamepublisher" id="40" value="West End Games"/>
    <statistics page="1">
      <ratings>
        <usersrated value="2"/>
        <average value="6.5"/>
        <bayesaverage value="0"/>
        <ranks>
          <rank type="subtype" id="1" name="boardgame" friendlyname="Board Game Rank" value="Not Ranked" bayesaverage="Not Ranked"/>
          <rank type="family" id="4664" name="wargames" friendlyname="War Game Rank" value="Not Ranked" bayesaverage="Not Ranked"/>
        </ranks>
        <stddev value="0.5"/>
        <median value="0"/>
        <owned value="20"/>
        <trading value="1"/>
        <wanting value="1"/>
        <wishing value="1"/>
        <numcomments value="0"/>
        <numweights value="1"/>
        <averageweight value="1"/>
      </ratings>
    </statistics>
  </item>
</items>
