<?xml version="1.0" encoding="utf-8"?>
<items termsofuse="https://boardgamegeek.com/xmlapi/termsofuse">
  <item type="boardgame" id="5481">
    <thumbnail>https://cf.geekdo-images.com/thumb/img/qI4R80oL9GPVz5gLRtAYoqJI20E=/fit-in/200x150/pic19936.jpg</thumbnail>
    <image>https://cf.geekdo-images.com/original/img/-MLncrNJiD4Kz3LI1BaFrs0n8Tg=/0x0/pic19936.jpg</image>
    <name type="primary" sortindex="1" value="Vive l'Empereur"/>
    <description>Vive l&amp;rsquo;Empereur is a game system that simulates, on a tactical level, the Napoleonic great battles.&amp;#10;&amp;#10;Line and &amp;eacute;lite Infantry, Light and Heavy Cavalry, Light, Heavy and Horse Artillery are the units that as Commander in Chief you have got under your command.&amp;#10;It takes but a few minutes to read the rules (only 3 pages, optional rules included), then deploy the units and you are ready for enjoy this game.&amp;#10;&amp;#10;The rules includes Napoleonic tactics, like cavalry counter-charge, form squares and artillery opportunity fire.&amp;#10;&amp;#10;Contents: &amp;#10;&amp;#10;    1 map (67x49,5 cm) front/back printed.&amp;#10;    180 pre-cut hexes (40 mm each), with 32 different kind of terrain.&amp;#10;    138 unit counters (20x35 mm each).&amp;#10;    72 colors order cards.&amp;#10;    8 special dice.&amp;#10;    1 dice pre-cut labels sheet.&amp;#10;    140 chips&amp;#10;    93 round (20 mm) counter stand. &amp;#10;    Waterloo, Ligny, Quatre Bras scenarios.&amp;#10;    Hypothetical battles scenario&amp;#10;    1 game rules&amp;#10;    2 reference sheets&amp;#10;&amp;#10;&amp;#10;&amp;#10;&amp;#10;Re-implemented by:  Advanced Vive l'Empereur&amp;#10;&amp;#10;</description>
    <yearpublished value="2003"/>
    <minplayers value="2"/>
    <maxplayers value="2"/>
    <poll name="suggested_numplayers" title="User Suggested Number of Players" totalvotes="0">
      <results numplayers="1">
        <result value="Best" numvotes="0"/>
        <result value="Recommended" numvotes="0"/>
        <result value="Not Recommended" numvotes="0"/>
      </results>
      <results numplayers="2">
        <result value="Best" numvotes="0"/>
        <result value="Recommended" numvotes="0"/>
        <result value="Not Recommended" numvotes="0"/>
      </results>
      <results numplayers="2+">
        <result value="Best" numvotes="0"/>
        <result value="Recommended" numvotes="0"/>
        <result value="Not Recommended" numvotes="0"/>
      </results>
    </poll>
    <playingtime value="120"/>
    <minplaytime value="120"/>
    <maxplaytime value="120"/>
    <minage value="12"/>
    <poll name="suggested_playerage" title="User Suggested Player Age" totalvotes="0">
	</poll>
    <poll name="language_dependence" title="Language Dependence" totalvotes="0">
	</poll>
    <link type="boardgamecategory" id="1051" value="Napoleonic"/>
    <link type="boardgamecategory" id="1019" value="Wargame"/>
    <link type="boardgamemechanic" id="2026" value="Hex-and-Counter"/>
    <link type="boardgamemechanic" id="2070" value="Simulation"/>
    <link type="boardgamedesigner" id="2060" value="Giovanni Crippa"/>
    <link type="boardgamepublisher" id="1281" value="GIOGAMES"/>
    <statistics page="1">
      <ratings>
        <usersrated value="63"/>
        <average value="6.88095"/>
        <bayesaverage value="5.55578"/>
        <ranks>
          <rank type="subtype" id="1" name="boardgame" friendlyname="Board Game Rank" value="8710" bayesaverage="5.55578"/>
          <rank type="family" id="4664" name="wargames" friendlyname="War Game Rank" value="1676" bayesaverage="5.82272"/>
        </ranks>
        <stddev value="1.81369"/>
        <median value="0"/>
        <owned value="110"/>
        <trading value="8"/>
        <wanting value="13"/>
        <wishing value="21"/>
        <numcomments value="42"/>
        <numweights value="5"/>
        <averageweight value="2.6"/>
      </ratings>
    </statistics>
  </item>
</items>
